myst/__init__.py
myst_client-0.0.1.dist-info/LICENSE
myst_client-0.0.1.dist-info/METADATA
myst_client-0.0.1.dist-info/WHEEL
myst_client-0.0.1.dist-info/top_level.txt
myst_client-0.0.1.dist-info/RECORD
